django_celery_oncommit/__init__.py
django_celery_oncommit-0.0.2.dist-info/METADATA
django_celery_oncommit-0.0.2.dist-info/RECORD
django_celery_oncommit-0.0.2.dist-info/WHEEL
django_celery_oncommit-0.0.2.dist-info/entry_points.txt
django_celery_oncommit-0.0.2.dist-info/top_level.txt
