Metadata-Version: 2.1
Name: django-celery-oncommit
Version: 0.0.2
Summary: Celery wrapper that delays tasks until the django transaction has committed
Home-page: https://gitlab.com/outofculture/django-celery-oncommit
Author: Martin Chase
Author-email: outofculture@gmail.com
License: BSD
Keywords: django celery
Platform: UNKNOWN
Requires-Dist: django (>=1.11)
Requires-Dist: celery (>=3.0)
